Workbook

Sheet Bulk Upload Template
A1: Name* | B1: Category* | C1: BranchName | D1: SellingPrice* | E1: CostPrice* | F1: Quantity* | G1: Vendor | H1: MinimumStockThreshold | I1: BulkSellingPrice | J1: BulkCostPrice | K1: BulkQuantity | L1: UnitsInBulk | M1: ExpiryDate (yyyy-MM-dd) | N1: SerialNumber
A2: Oxford Advanced Learner's Dictionary 10th Ed | B2: Educational Materials | C2: GodokPharm CAL | D2: 18500 | E2: 14200 | F2: 150 | G2: Oxford University Press | H2: 10 | I2: 175000 | J2: 135000 | K2: 12 | L2: 10 | M2: 2028-12-31 | N2: EDU-OUP-001
A3: Cambridge IGCSE Mathematics Coursebook | B3: Educational Materials | C3: GodokPharm CAL | D3: 22000 | E3: 17000 | F3: 120 | G3: Cambridge University Press | H3: 8 | I3: 210000 | J3: 162000 | K3: 10 | L3: 10 | M3: 2029-06-30 | N3: EDU-CUP-002
A4: Casio FX-991EX ClassWiz Scientific Calculator | B4: Educational Materials | C4: GodokPharm CAL | D4: 28500 | E4: 22500 | F4: 200 | G4: Casio Electronics | H4: 15 | I4: 270000 | J4: 215000 | K4: 15 | L4: 10 | M4: 2030-01-15 | N4: EDU-CAS-003
A5: Crayola Ultimate Crayon Collection 152 Count | B5: Educational Materials | C5: GodokPharm CAL | D5: 12500 | E5: 9200 | F5: 180 | G5: Crayola LLC | H5: 12 | I5: 118000 | J5: 87000 | K5: 15 | L5: 10 | M5: 2028-09-30 | N5: EDU-CRY-004
A6: Staedtler Noris HB Pencils (Box of 12) | B6: Educational Materials | C6: GodokPharm CAL | D6: 3200 | E6: 2100 | F6: 300 | G6: Staedtler Mars GmbH | H6: 25 | I6: 60000 | J6: 40000 | K6: 12 | L6: 20 | M6: 2029-11-30 | N6: EDU-STD-005
A7: Faber-Castell Classic Colour Pencils 36 Pack | B7: Educational Materials | C7: GodokPharm CAL | D7: 9800 | E7: 7200 | F7: 140 | G7: Faber-Castell AG | H7: 10 | I7: 92000 | J7: 68000 | K7: 10 | L7: 10 | M7: 2028-08-31 | N7: EDU-FBC-006
A8: Maped Technic 8-Piece Math Geometry Set | B8: Educational Materials | C8: GodokPharm CAL | D8: 4500 | E8: 3100 | F8: 250 | G8: Maped SAS | H8: 20 | I8: 84000 | J8: 58000 | K8: 10 | L8: 20 | M8: 2030-05-31 | N8: EDU-MAP-007
A9: Daler-Rowney A3 Spiral Artist Sketchbook 140gsm | B9: Educational Materials | C9: GodokPharm CAL | D9: 8500 | E9: 6000 | F9: 110 | G9: Daler-Rowney Ltd | H9: 8 | I9: 80000 | J9: 56000 | K9: 8 | L9: 10 | M9: 2028-03-31 | N9: EDU-DRW-008
A10: Schneider Slider Basic Ballpoint Pens Box of 10 | B10: Educational Materials | C10: GodokPharm CAL | D10: 5400 | E10: 3800 | F10: 220 | G10: Schneider Schreibgeräte | H10: 15 | I10: 50000 | J10: 35000 | K10: 15 | L10: 10 | M10: 2029-10-31 | N10: EDU-SCH-009
A11: Oxford Student Math Graph Notebook A4 200 Pages | B11: Educational Materials | C11: GodokPharm CAL | D11: 2800 | E11: 1900 | F11: 400 | G11: Oxford Paper Products | H11: 30 | I11: 52000 | J11: 35000 | K11: 15 | L11: 20 | M11: 2030-12-31 | N11: EDU-OUP-010

Sheet Dashboard & Summary
A1: QA BULK PRODUCT UPLOAD - EDUCATIONAL MATERIALS DASHBOARD
A3: TOTAL PRODUCTS | C3: TOTAL UNIT INVENTORY | E3: TOTAL INVENTORY INVESTMENT | G3: EXPECTED REVENUE
A4: =COUNTA('Bulk Upload Template'!A2:A11) -> 10 | C4: =SUM('Bulk Upload Template'!F2:F11) -> 2070 | E4: =SUMPRODUCT('Bulk Upload Template'!E2:E11, 'Bulk Upload Template'!F2:F11) -> 14995000 | G4: =SUMPRODUCT('Bulk Upload Template'!D2:D11, 'Bulk Upload Template'!F2:F11) -> 20065000
A6: Product Name | B6: Category | C6: Selling Price (₦) | D6: Cost Price (₦) | E6: Margin per Unit (₦) | F6: Profit Margin % | G6: Stock Qty | H6: Total Cost Value (₦) | I6: Total Sales Value (₦)
A7: ='Bulk Upload Template'!A2 -> Oxford Advanced Learner's Dictionary 10th Ed | B7: ='Bulk Upload Template'!B2 -> Educational Materials | C7: ='Bulk Upload Template'!D2 -> 18500 | D7: ='Bulk Upload Template'!E2 -> 14200 | E7: =C7-D7 -> 4300 | F7: =E7/C7 -> 0.23243243 | G7: ='Bulk Upload Template'!F2 -> 150 | H7: =D7*G7 -> 2130000 | I7: =C7*G7 -> 2775000
A8: ='Bulk Upload Template'!A3 -> Cambridge IGCSE Mathematics Coursebook | B8: ='Bulk Upload Template'!B3 -> Educational Materials | C8: ='Bulk Upload Template'!D3 -> 22000 | D8: ='Bulk Upload Template'!E3 -> 17000 | E8: =C8-D8 -> 5000 | F8: =E8/C8 -> 0.22727273 | G8: ='Bulk Upload Template'!F3 -> 120 | H8: =D8*G8 -> 2040000 | I8: =C8*G8 -> 2640000
A9: ='Bulk Upload Template'!A4 -> Casio FX-991EX ClassWiz Scientific Calculator | B9: ='Bulk Upload Template'!B4 -> Educational Materials | C9: ='Bulk Upload Template'!D4 -> 28500 | D9: ='Bulk Upload Template'!E4 -> 22500 | E9: =C9-D9 -> 6000 | F9: =E9/C9 -> 0.21052632 | G9: ='Bulk Upload Template'!F4 -> 200 | H9: =D9*G9 -> 4500000 | I9: =C9*G9 -> 5700000
A10: ='Bulk Upload Template'!A5 -> Crayola Ultimate Crayon Collection 152 Count | B10: ='Bulk Upload Template'!B5 -> Educational Materials | C10: ='Bulk Upload Template'!D5 -> 12500 | D10: ='Bulk Upload Template'!E5 -> 9200 | E10: =C10-D10 -> 3300 | F10: =E10/C10 -> 0.264 | G10: ='Bulk Upload Template'!F5 -> 180 | H10: =D10*G10 -> 1656000 | I10: =C10*G10 -> 2250000
A11: ='Bulk Upload Template'!A6 -> Staedtler Noris HB Pencils (Box of 12) | B11: ='Bulk Upload Template'!B6 -> Educational Materials | C11: ='Bulk Upload Template'!D6 -> 3200 | D11: ='Bulk Upload Template'!E6 -> 2100 | E11: =C11-D11 -> 1100 | F11: =E11/C11 -> 0.34375 | G11: ='Bulk Upload Template'!F6 -> 300 | H11: =D11*G11 -> 630000 | I11: =C11*G11 -> 960000
A12: ='Bulk Upload Template'!A7 -> Faber-Castell Classic Colour Pencils 36 Pack | B12: ='Bulk Upload Template'!B7 -> Educational Materials | C12: ='Bulk Upload Template'!D7 -> 9800 | D12: ='Bulk Upload Template'!E7 -> 7200 | E12: =C12-D12 -> 2600 | F12: =E12/C12 -> 0.26530612 | G12: ='Bulk Upload Template'!F7 -> 140 | H12: =D12*G12 -> 1008000 | I12: =C12*G12 -> 1372000
A13: ='Bulk Upload Template'!A8 -> Maped Technic 8-Piece Math Geometry Set | B13: ='Bulk Upload Template'!B8 -> Educational Materials | C13: ='Bulk Upload Template'!D8 -> 4500 | D13: ='Bulk Upload Template'!E8 -> 3100 | E13: =C13-D13 -> 1400 | F13: =E13/C13 -> 0.31111111 | G13: ='Bulk Upload Template'!F8 -> 250 | H13: =D13*G13 -> 775000 | I13: =C13*G13 -> 1125000
A14: ='Bulk Upload Template'!A9 -> Daler-Rowney A3 Spiral Artist Sketchbook 140gsm | B14: ='Bulk Upload Template'!B9 -> Educational Materials | C14: ='Bulk Upload Template'!D9 -> 8500 | D14: ='Bulk Upload Template'!E9 -> 6000 | E14: =C14-D14 -> 2500 | F14: =E14/C14 -> 0.29411765 | G14: ='Bulk Upload Template'!F9 -> 110 | H14: =D14*G14 -> 660000 | I14: =C14*G14 -> 935000
A15: ='Bulk Upload Template'!A10 -> Schneider Slider Basic Ballpoint Pens Box of 10 | B15: ='Bulk Upload Template'!B10 -> Educational Materials | C15: ='Bulk Upload Template'!D10 -> 5400 | D15: ='Bulk Upload Template'!E10 -> 3800 | E15: =C15-D15 -> 1600 | F15: =E15/C15 -> 0.2962963 | G15: ='Bulk Upload Template'!F10 -> 220 | H15: =D15*G15 -> 836000 | I15: =C15*G15 -> 1188000
A16: ='Bulk Upload Template'!A11 -> Oxford Student Math Graph Notebook A4 200 Pages | B16: ='Bulk Upload Template'!B11 -> Educational Materials | C16: ='Bulk Upload Template'!D11 -> 2800 | D16: ='Bulk Upload Template'!E11 -> 1900 | E16: =C16-D16 -> 900 | F16: =E16/C16 -> 0.32142857 | G16: ='Bulk Upload Template'!F11 -> 400 | H16: =D16*G16 -> 760000 | I16: =C16*G16 -> 1120000
A17: TOTAL / AVERAGE SUMMARY | B17: 10 Products | C17: =AVERAGE(C7:C16) -> 11570 | D17: =AVERAGE(D7:D16) -> 8700 | E17: =AVERAGE(E7:E16) -> 2870 | F17: =AVERAGE(F7:F16) -> 0.27662412 | G17: =SUM(G7:G16) -> 2070 | H17: =SUM(H7:H16) -> 14995000 | I17: =SUM(I7:I16) -> 20065000

Sheet QA Test Matrix
A1: QA BULK UPLOAD TEST MATRIX & VALIDATION RESULTS
A3: Test ID | B3: Validation Scope | C3: Scenario Description | D3: Expected Behavior | E3: Validation Rule | F3: Status
A4: TC-EDU-001 | B4: Category Rule | C4: Validate all 10 products are assigned to 'Educational Materials' | D4: Import successful with category set to Educational Materials | E4: Category* == 'Educational Materials' | F4: PASSED
A5: TC-EDU-002 | B5: Expiry Date Future Rule | C5: Verify ExpiryDate is strictly in the future (> current date) | D5: All 10 products have valid future dates (2028 - 2030) | E5: ExpiryDate > Current Date | F5: PASSED
A6: TC-EDU-003 | B6: Mandatory Fields Check | C6: Verify mandatory fields (* marked) are populated | D6: 100% compliance with zero null value errors on upload | E6: NOT NULL(Name*, Category*, Price*, Qty*) | F6: PASSED
A7: TC-EDU-004 | B7: Numeric & Price Format | C7: Ensure SellingPrice*, CostPrice*, Quantity* are valid integers | D7: Correctly parsed as numbers without data type mismatch | E7: ISNUMERIC(Price, Qty) | F7: PASSED
A8: TC-EDU-005 | B8: Margin Integrity Check | C8: Verify SellingPrice > CostPrice across all 10 products | D8: Positive gross margin confirmed across all educational items | E8: SellingPrice* > CostPrice* | F8: PASSED
A9: TC-EDU-006 | B9: SKU Uniqueness | C9: Check SerialNumber (EDU-OUP-001 to EDU-OUP-010) uniqueness | D9: All 10 serial numbers registered as unique SKUs | E9: COUNT(SerialNumber) == 10 | F9: PASSED
A10: TC-EDU-007 | B10: Bulk Pricing Rule | C10: Validate bulk pricing offers discount relative to single unit | D10: Bulk unit price is lower than single unit selling price | E10: BulkSellingPrice < (SellingPrice * UnitsInBulk) | F10: PASSED
A11: TC-EDU-008 | B11: Reorder Level Check | C11: Verify MinimumStockThreshold field is correctly defined | D11: Reorder threshold properly set for stock alert triggers | E11: MinimumStockThreshold >= 1 | F11: PASSED
A12: TC-EDU-009 | B12: Vendor Association | C12: Ensure Vendor strings map to approved publishing/educational vendors | D12: Vendors (Oxford, Cambridge, Casio, Crayola) cleanly imported | E12: Vendor IS NOT NULL | F12: PASSED
A13: TC-EDU-010 | B13: Template Schema Match | C13: Ensure file columns match standard system template header exact strings | D13: Column mapping verified with 100% schema alignment | E13: Header String Match == TRUE | F13: PASSED
